catalyst/__init__.py
catalyst/types.py
catalyst/services/__init__.py
catalyst/services/gemini.py
catalyst/services/hunter.py
catalyst/services/serpapi.py
catalyst/services/twitter.py
catalyst_sdk-0.1.0.dist-info/METADATA
catalyst_sdk-0.1.0.dist-info/WHEEL
catalyst_sdk-0.1.0.dist-info/licenses/LICENSE
catalyst_sdk-0.1.0.dist-info/RECORD
