Metadata-Version: 2.4
Name: catalyst-sdk
Version: 0.1.0
Summary: AI-powered outbound prospect finder - Generate Google dorks, find emails, and craft personalized outreach
Project-URL: Homepage, https://github.com/namit/catalyst-sdk
Project-URL: Repository, https://github.com/namit/catalyst-sdk
Project-URL: Issues, https://github.com/namit/catalyst-sdk/issues
Author: Namit
License-Expression: MIT
License-File: LICENSE
Keywords: ai,email-finder,gemini,google-dorks,hunter,lead-generation,outbound,prospecting,sales,serpapi
Classifier: Development Status :: 4 - Beta
Classifier: Intended Audience :: Developers
Classifier: License :: OSI Approved :: MIT License
Classifier: Programming Language :: Python :: 3
Classifier: Programming Language :: Python :: 3.9
Classifier: Programming Language :: Python :: 3.10
Classifier: Programming Language :: Python :: 3.11
Classifier: Programming Language :: Python :: 3.12
Classifier: Topic :: Software Development :: Libraries :: Python Modules
Requires-Python: >=3.9
Requires-Dist: google-generativeai>=0.4.0
Requires-Dist: httpx>=0.25.0
Requires-Dist: pydantic>=2.0.0
Provides-Extra: dev
Requires-Dist: pytest-asyncio>=0.21.0; extra == 'dev'
Requires-Dist: pytest>=7.0.0; extra == 'dev'
Requires-Dist: ruff>=0.1.0; extra == 'dev'
